pyawr/__init__.py
pyawr/mwoffice.py
pyawr-24.1.1.dist-info/LICENSE
pyawr-24.1.1.dist-info/METADATA
pyawr-24.1.1.dist-info/WHEEL
pyawr-24.1.1.dist-info/top_level.txt
pyawr-24.1.1.dist-info/RECORD
