Metadata-Version: 2.1
Name: pyawr
Version: 24.1.1
Summary: Python Interface Module for AWR Design Environment
Author: AWR
Classifier: Programming Language :: Python :: 3
Classifier: License :: OSI Approved :: MIT License
Classifier: Operating System :: OS Independent
Requires-Python: >=3.9
License-File: LICENSE
Requires-Dist: pywin32
